LICENSE
README.md
pyproject.toml
setup.py
bfxapi/__init__.py
bfxapi/_client.py
bfxapi/_version.py
bfxapi/exceptions.py
bfxapi/py.typed
bfxapi/_utils/__init__.py
bfxapi/_utils/json_decoder.py
bfxapi/_utils/json_encoder.py
bfxapi/_utils/logging.py
bfxapi/rest/__init__.py
bfxapi/rest/_bfx_rest_interface.py
bfxapi/rest/exceptions.py
bfxapi/rest/_interface/__init__.py
bfxapi/rest/_interface/interface.py
bfxapi/rest/_interface/middleware.py
bfxapi/rest/_interfaces/__init__.py
bfxapi/rest/_interfaces/rest_auth_endpoints.py
bfxapi/rest/_interfaces/rest_public_endpoints.py
bfxapi/types/__init__.py
bfxapi/types/dataclasses.py
bfxapi/types/labeler.py
bfxapi/types/notification.py
bfxapi/types/serializers.py
bfxapi/websocket/__init__.py
bfxapi/websocket/_connection.py
bfxapi/websocket/exceptions.py
bfxapi/websocket/subscriptions.py
bfxapi/websocket/_client/__init__.py
bfxapi/websocket/_client/bfx_websocket_bucket.py
bfxapi/websocket/_client/bfx_websocket_client.py
bfxapi/websocket/_client/bfx_websocket_inputs.py
bfxapi/websocket/_event_emitter/__init__.py
bfxapi/websocket/_event_emitter/bfx_event_emitter.py
bfxapi/websocket/_handlers/__init__.py
bfxapi/websocket/_handlers/auth_events_handler.py
bfxapi/websocket/_handlers/public_channels_handler.py
bitfinex_api_py.egg-info/PKG-INFO
bitfinex_api_py.egg-info/SOURCES.txt
bitfinex_api_py.egg-info/dependency_links.txt
bitfinex_api_py.egg-info/requires.txt
bitfinex_api_py.egg-info/top_level.txt